poseidon_wep_sdk/__init__.py
poseidon_wep_sdk/config.py
poseidon_wep_sdk/registry.py
poseidon_wep_sdk/runner.py
poseidon_wep_sdk/server.py
poseidon_wep_sdk/types.py
poseidon_wep_sdk/wep_server.py
poseidon_wep_sdk/generated/__init__.py
poseidon_wep_sdk/generated/execution/v1/__init__.py
poseidon_wep_sdk/generated/execution/v1/execution_pb2.py
poseidon_wep_sdk/generated/execution/v1/execution_pb2_grpc.py
poseidon_wep_sdk-0.2.0.dist-info/METADATA
poseidon_wep_sdk-0.2.0.dist-info/WHEEL
poseidon_wep_sdk-0.2.0.dist-info/top_level.txt
poseidon_wep_sdk-0.2.0.dist-info/RECORD
